secure_config_manager/__init__.py
secure_config_manager/config_manager.py
secure_config_manager/singleton.py
secure_config_manager-0.0.2.dist-info/LICENSE
secure_config_manager-0.0.2.dist-info/METADATA
secure_config_manager-0.0.2.dist-info/WHEEL
secure_config_manager-0.0.2.dist-info/top_level.txt
secure_config_manager-0.0.2.dist-info/RECORD
