Metadata-Version: 2.1
Name: secure-config-manager
Version: 0.0.2
Summary: Secure config manager. Access app secrets easily without sharing them to public.
Home-page: https://github.com/paulin-mipt/secure-config-manager
Author: Polina Matavina
License: UNKNOWN
Project-URL: Bug Tracker, https://github.com/paulin-mipt/secure-config-manager/issues
Platform: UNKNOWN
Classifier: Programming Language :: Python :: 3
Classifier: License :: OSI Approved :: MIT License
Classifier: Operating System :: OS Independent
Requires-Python: >=3.0
License-File: LICENSE
